{"uuid":"86de126a-05a8-449e-9576-ad9457b1aa1e","body_part":{"cell_count":"1","organ":"brain","name":"arcuate nucleus of hypothalamus"},"donor":{"ncbi_taxon":"10090","sex":"male","species":"House mouse","id":"POMC_GFP_I_54","uuid":"af861fed-eb2b-4cd9-bf8e-316bc73fc8d9"},"protocols":[{"description":"qPCR only","type":"nucleic acid library construction protocol"},{"description":"Illumina HiSeq 2500","type":"nucleic acid sequencing protocol"}],"enrichment":"POMC+","ena_sample":"ERS639389","submitted_id":"ERS639389","short_label":"POMC+ from mouse 54","long_label":"POMC+ neurons from arcuate nucleus of hypothalamus of mouse 54"}
